scims/__init__.py
scims/__main__.py
scims/classification.py
scims/helpers.py
scims/process_idxstats.py
scims/utils.py
scims/data/training_data_hmp_1000x_normalizedXY.txt
scims-1.0.1.dist-info/licenses/LICENSE
tests/.DS_Store
tests/__init__.py
tests/test_classification.py
tests/test_helpers.py
tests/test_process_idxstats.py
tests/test_run.py
tests/test_utils.py
tests/__pycache__/__init__.cpython-39.pyc
tests/__pycache__/test_classification.cpython-39-pytest-8.4.2.pyc
tests/__pycache__/test_helpers.cpython-39-pytest-8.4.2.pyc
tests/__pycache__/test_process_idxstats.cpython-39-pytest-8.4.2.pyc
tests/__pycache__/test_run.cpython-39-pytest-8.4.2.pyc
tests/__pycache__/test_utils.cpython-39-pytest-8.4.2.pyc
scims-1.0.1.dist-info/METADATA
scims-1.0.1.dist-info/WHEEL
scims-1.0.1.dist-info/entry_points.txt
scims-1.0.1.dist-info/top_level.txt
scims-1.0.1.dist-info/RECORD
