Metadata-Version: 2.4
Name: SCiMS
Version: 1.0.1
Summary: SCiMS: Sex Calling in Metagenomic Sequences
Home-page: https://github.com/hanhntran/SCiMS
Author: Hanh Tran
Classifier: Programming Language :: Python :: 3
Classifier: Operating System :: OS Independent
Classifier: Development Status :: 4 - Beta
Requires-Python: >=3.9
License-File: LICENSE
Requires-Dist: numpy
Requires-Dist: pandas
Requires-Dist: scipy
Requires-Dist: setuptools
Dynamic: author
Dynamic: classifier
Dynamic: description
Dynamic: description-content-type
Dynamic: home-page
Dynamic: license-file
Dynamic: requires-dist
Dynamic: requires-python
Dynamic: summary
